ai_agent_cli/__init__.py
ai_agent_cli/ai_agent.py
ai_agent_cli/cli.py
ai_agent_cli-0.1.dist-info/LICENSE
ai_agent_cli-0.1.dist-info/METADATA
ai_agent_cli-0.1.dist-info/WHEEL
ai_agent_cli-0.1.dist-info/entry_points.txt
ai_agent_cli-0.1.dist-info/top_level.txt
ai_agent_cli-0.1.dist-info/RECORD
